liblinea.py
liblinea_ai.py
liblinea_data.py
liblinea_math.py
liblinea_network.py
liblinea_weblet.py
liblinea-2.2.1.dist-info/licenses/LICENSE
liblinea-2.2.1.dist-info/METADATA
liblinea-2.2.1.dist-info/WHEEL
liblinea-2.2.1.dist-info/top_level.txt
liblinea-2.2.1.dist-info/RECORD
