Metadata-Version: 2.4
Name: liblinea
Version: 2.2.1
Summary: The Core Module(s) for Linea Programming Language
Home-page: https://github.com/gauthamnair2005/LibLinea
Author: Gautham Nair
Author-email: gautham.nair.2005@gmail.com
Classifier: Programming Language :: Python :: 3
Classifier: License :: OSI Approved :: MIT License
Classifier: Operating System :: OS Independent
Requires-Python: >=3.12
License-File: LICENSE
Dynamic: author
Dynamic: author-email
Dynamic: classifier
Dynamic: description
Dynamic: description-content-type
Dynamic: home-page
Dynamic: license-file
Dynamic: requires-python
Dynamic: summary
